file/__init__.py
file/file.py
xintool/__init__.py
xintool/file.py
xintool-0.0.7.dist-info/METADATA
xintool-0.0.7.dist-info/WHEEL
xintool-0.0.7.dist-info/top_level.txt
xintool-0.0.7.dist-info/RECORD
