Metadata-Version: 2.1
Name: xintool
Version: 0.0.7
Summary: python opensource tools
Home-page: http://blog.jiangyixin.top
Author: jiangyixin
Author-email: jyx15221613915@gmail.com
License: UNKNOWN
Keywords: tools library
Platform: UNKNOWN
